MANIFEST.in
setup.cfg
setup.py
tw/__init__.py
tw.forms.egg-info/PKG-INFO
tw.forms.egg-info/SOURCES.txt
tw.forms.egg-info/dependency_links.txt
tw.forms.egg-info/entry_points.txt
tw.forms.egg-info/namespace_packages.txt
tw.forms.egg-info/not-zip-safe
tw.forms.egg-info/requires.txt
tw.forms.egg-info/top_level.txt
tw/forms/__init__.py
tw/forms/calendars.py
tw/forms/core.py
tw/forms/datagrid.py
tw/forms/fields.py
tw/forms/release.py
tw/forms/samples.py
tw/forms/validators.py
tw/forms/static/grid.css
tw/forms/static/calendar/calendar-blue.css
tw/forms/static/calendar/calendar-blue2.css
tw/forms/static/calendar/calendar-brown.css
tw/forms/static/calendar/calendar-green.css
tw/forms/static/calendar/calendar-setup.js
tw/forms/static/calendar/calendar-system.css
tw/forms/static/calendar/calendar-tas.css
tw/forms/static/calendar/calendar-win2k-1.css
tw/forms/static/calendar/calendar-win2k-2.css
tw/forms/static/calendar/calendar-win2k-cold-1.css
tw/forms/static/calendar/calendar-win2k-cold-2.css
tw/forms/static/calendar/calendar.js
tw/forms/static/calendar/menuarrow.gif
tw/forms/static/calendar/menuarrow2.gif
tw/forms/static/calendar/lang/calendar-af.js
tw/forms/static/calendar/lang/calendar-bg-cp1251.js
tw/forms/static/calendar/lang/calendar-bg.js
tw/forms/static/calendar/lang/calendar-ca.js
tw/forms/static/calendar/lang/calendar-cs-cp1250.js
tw/forms/static/calendar/lang/calendar-cs.js
tw/forms/static/calendar/lang/calendar-da.js
tw/forms/static/calendar/lang/calendar-de.js
tw/forms/static/calendar/lang/calendar-de_at.js
tw/forms/static/calendar/lang/calendar-de_de.js
tw/forms/static/calendar/lang/calendar-el.js
tw/forms/static/calendar/lang/calendar-en.js
tw/forms/static/calendar/lang/calendar-es.js
tw/forms/static/calendar/lang/calendar-fi.js
tw/forms/static/calendar/lang/calendar-fr.js
tw/forms/static/calendar/lang/calendar-he.js
tw/forms/static/calendar/lang/calendar-hr.js
tw/forms/static/calendar/lang/calendar-hu-cp1252.js
tw/forms/static/calendar/lang/calendar-hu.js
tw/forms/static/calendar/lang/calendar-it.js
tw/forms/static/calendar/lang/calendar-ja.js
tw/forms/static/calendar/lang/calendar-ko-euc_kr.js
tw/forms/static/calendar/lang/calendar-ko.js
tw/forms/static/calendar/lang/calendar-lt.js
